libghdl/__init__.py
libghdl/version.py
libghdl/thin/__init__.py
libghdl/thin/errorout.py
libghdl/thin/errorout_console.py
libghdl/thin/errorout_memory.py
libghdl/thin/files_map.py
libghdl/thin/files_map_editor.py
libghdl/thin/flags.py
libghdl/thin/libraries.py
libghdl/thin/name_table.py
libghdl/thin/std_names.py
libghdl/thin/vhdl/__init__.py
libghdl/thin/vhdl/canon.py
libghdl/thin/vhdl/elocations.py
libghdl/thin/vhdl/flists.py
libghdl/thin/vhdl/formatters.py
libghdl/thin/vhdl/ieee.py
libghdl/thin/vhdl/lists.py
libghdl/thin/vhdl/nodes.py
libghdl/thin/vhdl/nodes_meta.py
libghdl/thin/vhdl/nodes_utils.py
libghdl/thin/vhdl/parse.py
libghdl/thin/vhdl/pyutils.py
libghdl/thin/vhdl/scanner.py
libghdl/thin/vhdl/sem.py
libghdl/thin/vhdl/sem_lib.py
libghdl/thin/vhdl/std_package.py
libghdl/thin/vhdl/tokens.py
vhdl_langserver/__init__.py
vhdl_langserver/document.py
vhdl_langserver/lsp.py
vhdl_langserver/lsptools.py
vhdl_langserver/main.py
vhdl_langserver/references.py
vhdl_langserver/symbols.py
vhdl_langserver/version.py
vhdl_langserver/vhdl_ls.py
vhdl_langserver/workspace.py
pyghdl-1.0.dev0.dist-info/METADATA
pyghdl-1.0.dev0.dist-info/WHEEL
pyghdl-1.0.dev0.dist-info/entry_points.txt
pyghdl-1.0.dev0.dist-info/top_level.txt
pyghdl-1.0.dev0.dist-info/RECORD
