Metadata-Version: 2.1
Name: pyghdl
Version: 1.0.dev0
Summary: VHDL Language Server and interface to ghdl, a VHDL analyzer
Home-page: http://github.com/ghdl/ghdl
Author: Tristan Gingold
Author-email: tgingold@free.fr
License: GPL-2.0-or-later
Platform: UNKNOWN
Requires-Dist: attrs
